punkweb_bb/__init__.py
punkweb_bb/admin.py
punkweb_bb/admin_forms.py
punkweb_bb/apps.py
punkweb_bb/bbcode.py
punkweb_bb/context_processors.py
punkweb_bb/decorators.py
punkweb_bb/forms.py
punkweb_bb/guests.py
punkweb_bb/middleware.py
punkweb_bb/mixins.py
punkweb_bb/models.py
punkweb_bb/pagination.py
punkweb_bb/response.py
punkweb_bb/searching.py
punkweb_bb/settings.py
punkweb_bb/signals.py
punkweb_bb/tests.py
punkweb_bb/urls.py
punkweb_bb/utils.py
punkweb_bb/views.py
punkweb_bb/widgets.py
punkweb_bb/__pycache__/__init__.cpython-311.pyc
punkweb_bb/__pycache__/admin.cpython-311.pyc
punkweb_bb/__pycache__/admin_forms.cpython-311.pyc
punkweb_bb/__pycache__/apps.cpython-311.pyc
punkweb_bb/__pycache__/bbcode.cpython-311.pyc
punkweb_bb/__pycache__/bbcode_tags.cpython-311.pyc
punkweb_bb/__pycache__/context_processors.cpython-311.pyc
punkweb_bb/__pycache__/decorators.cpython-311.pyc
punkweb_bb/__pycache__/forms.cpython-311.pyc
punkweb_bb/__pycache__/guests.cpython-311.pyc
punkweb_bb/__pycache__/middleware.cpython-311.pyc
punkweb_bb/__pycache__/mixins.cpython-311.pyc
punkweb_bb/__pycache__/models.cpython-311.pyc
punkweb_bb/__pycache__/pagination.cpython-311.pyc
punkweb_bb/__pycache__/parsers.cpython-311.pyc
punkweb_bb/__pycache__/response.cpython-311.pyc
punkweb_bb/__pycache__/searching.cpython-311.pyc
punkweb_bb/__pycache__/settings.cpython-311.pyc
punkweb_bb/__pycache__/signals.cpython-311.pyc
punkweb_bb/__pycache__/sitemap.cpython-311.pyc
punkweb_bb/__pycache__/tags.cpython-311.pyc
punkweb_bb/__pycache__/tests.cpython-311.pyc
punkweb_bb/__pycache__/urls.cpython-311.pyc
punkweb_bb/__pycache__/utils.cpython-311.pyc
punkweb_bb/__pycache__/views.cpython-311.pyc
punkweb_bb/__pycache__/widgets.cpython-311.pyc
punkweb_bb/migrations/0001_initial.py
punkweb_bb/migrations/0002_thread_view_count.py
punkweb_bb/migrations/0003_alter_thread_options.py
punkweb_bb/migrations/0004_groupstyle.py
punkweb_bb/migrations/0005_alter_thread_options.py
punkweb_bb-0.5.0.dist-info/LICENSE
punkweb_bb-0.5.0.dist-info/METADATA
punkweb_bb-0.5.0.dist-info/WHEEL
punkweb_bb-0.5.0.dist-info/top_level.txt
punkweb_bb-0.5.0.dist-info/RECORD
