Metadata-Version: 2.1
Name: punkweb-bb
Version: 0.5.0
Summary: Django application that provides a simple and modern forum board software for your Django website.
Home-page: https://github.com/Punkweb/PunkwebBB
Author: Punkweb
Author-email: punkwebnet@gmail.com
License: BSD-3-Clause
Classifier: Environment :: Web Environment
Classifier: Framework :: Django
Classifier: Intended Audience :: Developers
Classifier: License :: OSI Approved :: BSD License
Classifier: Operating System :: OS Independent
Classifier: Programming Language :: Python
Classifier: Programming Language :: Python :: 3
License-File: LICENSE
Requires-Dist: django >=4.0
Requires-Dist: bbcode
Requires-Dist: markdown
Requires-Dist: pillow
Requires-Dist: expiringdict
